go2pdb/__init__.py
go2pdb/__main__.py
go2pdb/blast.py
go2pdb/cluster.py
go2pdb/pdb.py
go2pdb/go/__init__.py
go2pdb/go/goa.py
go2pdb/go/uniprot.py
go2pdb-1.0.1.dist-info/LICENSE.md
go2pdb-1.0.1.dist-info/METADATA
go2pdb-1.0.1.dist-info/WHEEL
go2pdb-1.0.1.dist-info/entry_points.txt
go2pdb-1.0.1.dist-info/top_level.txt
go2pdb-1.0.1.dist-info/RECORD
