Metadata-Version: 2.1
Name: go2pdb
Version: 1.0.1
Summary: This code identifies Protein Data Bank (PDB) entries with specific Gene Ontology (GO) annotations.
Home-page: https://github.com/Electrostatics/go2pdb
Author: Nathan Baker
Author-email: nathanandrewbaker@gmail.com
License: UNKNOWN
Keywords: science chemistry biophysics biochemistry
Platform: UNKNOWN
Classifier: Development Status :: 4 - Beta
Classifier: Environment :: Console
Classifier: Intended Audience :: Science/Research
Classifier: License :: OSI Approved :: BSD License
Classifier: Natural Language :: English
Classifier: Operating System :: OS Independent
Classifier: Programming Language :: Python :: 3.8
Classifier: Programming Language :: Python :: 3.9
Classifier: Topic :: Scientific/Engineering :: Bio-Informatics
Classifier: Topic :: Scientific/Engineering :: Chemistry
Classifier: Topic :: Scientific/Engineering :: Physics
Requires-Python: >=3.8
Requires-Dist: requests
Requires-Dist: biopython
Requires-Dist: pandas
Requires-Dist: openpyxl
Requires-Dist: numpy
Requires-Dist: mmcif-pdbx
